[{
    "index": "A",
    "users": [
      {
        "name": "Ackod",
        "tel": "13214015664"
      },
      {
        "name": "Aief",
        "tel": "13161004972"
      },
      {
        "name": "Axltab",
        "tel": "13107707817"
      },
      {
        "name": "Awcm",
        "tel": "18740258618"
      },
      {
        "name": "Atifgp",
        "tel": "13388609986"
      }
    ]
  },
  {
    "index": "B",
    "users": [
      {
        "name": "Bkeh",
        "tel": "13047626589"
      },
      {
        "name": "Bpbwsv",
        "tel": "13502203861"
      },
      {
        "name": "Bbvnrg",
        "tel": "13556129149"
      }
    ]
  },
  {
    "index": "C",
    "users": [
      {
        "name": "Cabnu",
        "tel": "13388260715"
      },
      {
        "name": "Cpte",
        "tel": "13834861705"
      },
      {
        "name": "Cokvilj",
        "tel": "13387794210"
      },
      {
        "name": "Crzmvq",
        "tel": "13361005974"
      },
      {
        "name": "Cuxd",
        "tel": "18751437670"
      }
    ]
  },
  {
    "index": "D",
    "users": [
      {
        "name": "Doslic",
        "tel": "13344748295"
      },
      {
        "name": "Dtsbgn",
        "tel": "13769262345"
      },
      {
        "name": "Dbrvaqc",
        "tel": "13895098794"
      },
      {
        "name": "Djmbf",
        "tel": "13398119834"
      },
      {
        "name": "Dghdsu",
        "tel": "13172193928"
      },
      {
        "name": "Dkkwqxh",
        "tel": "13569150577"
      }
    ]
  },
  {
    "index": "E",
    "users": [
      {
        "name": "Erkfaby",
        "tel": "13555682498"
      },
      {
        "name": "Embbfrw",
        "tel": "13552893371"
      },
      {
        "name": "Ejjc",
        "tel": "13183176879"
      }
    ]
  },
  {
    "index": "F",
    "users": [
      {
        "name": "Fteu",
        "tel": "13764237637"
      },
      {
        "name": "Fbqpru",
        "tel": "17091182665"
      },
      {
        "name": "Fvkxhxl",
        "tel": "13887857562"
      },
      {
        "name": "Fnwfav",
        "tel": "13591364206"
      },
      {
        "name": "Flzyhth",
        "tel": "13122613425"
      },
      {
        "name": "Fxhtemr",
        "tel": "13170521302"
      }
    ]
  },
  {
    "index": "G",
    "users": [
      {
        "name": "Gfhqp",
        "tel": "13067016998"
      },
      {
        "name": "Gmjzge",
        "tel": "13834516082"
      },
      {
        "name": "Gopavt",
        "tel": "18740545305"
      },
      {
        "name": "Gxykao",
        "tel": "18794001311"
      },
      {
        "name": "Gztgeir",
        "tel": "13578747769"
      },
      {
        "name": "Gfomt",
        "tel": "13721162815"
      }
    ]
  },
  {
    "index": "H",
    "users": [
      {
        "name": "Hzotr",
        "tel": "13581718191"
      },
      {
        "name": "Hhwl",
        "tel": "13338429453"
      },
      {
        "name": "Hplz",
        "tel": "13283088156"
      },
      {
        "name": "Hsxyjz",
        "tel": "17069948615"
      },
      {
        "name": "Htpa",
        "tel": "13051090633"
      }
    ]
  },
  {
    "index": "I",
    "users": [
      {
        "name": "Inyfgtw",
        "tel": "13275038444"
      },
      {
        "name": "Iqirdrv",
        "tel": "13320666376"
      },
      {
        "name": "Ivfsw",
        "tel": "18778467444"
      }
    ]
  },
  {
    "index": "J",
    "users": [
      {
        "name": "Jbqvisa",
        "tel": "13230217612"
      },
      {
        "name": "Jfftfjo",
        "tel": "13327822557"
      },
      {
        "name": "Jkgg",
        "tel": "13856334300"
      },
      {
        "name": "Jhvyn",
        "tel": "13580474860"
      }
    ]
  },
  {
    "index": "K",
    "users": [
      {
        "name": "Kzspb",
        "tel": "13769096600"
      },
      {
        "name": "Kxgx",
        "tel": "13195713177"
      },
      {
        "name": "Krnrzk",
        "tel": "13748917254"
      },
      {
        "name": "Krdv",
        "tel": "13362670208"
      },
      {
        "name": "Kqdawe",
        "tel": "17067384945"
      }
    ]
  },
  {
    "index": "L",
    "users": [
      {
        "name": "Lgrrd",
        "tel": "13830936102"
      },
      {
        "name": "Lfnqci",
        "tel": "13227908559"
      },
      {
        "name": "Lyju",
        "tel": "18774591202"
      },
      {
        "name": "Ljzdm",
        "tel": "13058393183"
      }
    ]
  },
  {
    "index": "M",
    "users": [
      {
        "name": "Mvzr",
        "tel": "18769663312"
      },
      {
        "name": "Mtuvi",
        "tel": "13285856026"
      },
      {
        "name": "Miyo",
        "tel": "13150804657"
      }
    ]
  },
  {
    "index": "N",
    "users": [
      {
        "name": "Nmkdy",
        "tel": "13056684324"
      },
      {
        "name": "Nviepc",
        "tel": "13881316004"
      },
      {
        "name": "Nmsdx",
        "tel": "18792646521"
      },
      {
        "name": "Ngccnqa",
        "tel": "17068545868"
      }
    ]
  },
  {
    "index": "O",
    "users": [
      {
        "name": "Onsq",
        "tel": "17000768334"
      },
      {
        "name": "Osjxsot",
        "tel": "13523722820"
      },
      {
        "name": "Olkquc",
        "tel": "13301738316"
      },
      {
        "name": "Oqrsu",
        "tel": "13810326137"
      },
      {
        "name": "Octo",
        "tel": "13210089283"
      }
    ]
  },
  {
    "index": "P",
    "users": [
      {
        "name": "Puxlgj",
        "tel": "17055863811"
      },
      {
        "name": "Pktplw",
        "tel": "17031309202"
      },
      {
        "name": "Phkaekx",
        "tel": "18757618724"
      },
      {
        "name": "Piyspmf",
        "tel": "17022041000"
      },
      {
        "name": "Pquuu",
        "tel": "13215753088"
      }
    ]
  },
  {
    "index": "Q",
    "users": [
      {
        "name": "Qmdircq",
        "tel": "13791319822"
      },
      {
        "name": "Qjeu",
        "tel": "18748909937"
      },
      {
        "name": "Qpymdfc",
        "tel": "13357129825"
      },
      {
        "name": "Qqiyd",
        "tel": "13750153849"
      },
      {
        "name": "Qkcxhs",
        "tel": "13028190814"
      },
      {
        "name": "Qrir",
        "tel": "18931228640"
      }
    ]
  },
  {
    "index": "R",
    "users": [
      {
        "name": "Romvxx",
        "tel": "13578593581"
      },
      {
        "name": "Rxsts",
        "tel": "13067425478"
      },
      {
        "name": "Rdhvg",
        "tel": "13589070609"
      },
      {
        "name": "Rpbj",
        "tel": "13078372470"
      },
      {
        "name": "Rrlrezw",
        "tel": "13855719307"
      }
    ]
  },
  {
    "index": "S",
    "users": [
      {
        "name": "Selksd",
        "tel": "13098753386"
      },
      {
        "name": "Ssgwiuk",
        "tel": "13093684918"
      },
      {
        "name": "Spyzl",
        "tel": "13360819297"
      },
      {
        "name": "Shzo",
        "tel": "13802362513"
      },
      {
        "name": "Stvoo",
        "tel": "13519885536"
      }
    ]
  },
  {
    "index": "T",
    "users": [
      {
        "name": "Txxb",
        "tel": "13536106762"
      },
      {
        "name": "Trdpl",
        "tel": "13854005790"
      },
      {
        "name": "Ttepsqq",
        "tel": "18974073409"
      },
      {
        "name": "Tpsbxf",
        "tel": "17019907012"
      },
      {
        "name": "Twqn",
        "tel": "18948807799"
      },
      {
        "name": "Tvwnwwf",
        "tel": "13041006034"
      }
    ]
  },
  {
    "index": "U",
    "users": [
      {
        "name": "Uzxvt",
        "tel": "13100583156"
      },
      {
        "name": "Udfhznh",
        "tel": "13786201874"
      },
      {
        "name": "Uakpyy",
        "tel": "18984799834"
      }
    ]
  },
  {
    "index": "V",
    "users": [
      {
        "name": "Vwoai",
        "tel": "13700432587"
      },
      {
        "name": "Velqfy",
        "tel": "13115221553"
      },
      {
        "name": "Visiib",
        "tel": "18702924162"
      }
    ]
  },
  {
    "index": "W",
    "users": [
      {
        "name": "Wdmh",
        "tel": "13592591829"
      },
      {
        "name": "Wqow",
        "tel": "17005608395"
      },
      {
        "name": "Wgfdbk",
        "tel": "18991373979"
      },
      {
        "name": "Wcvu",
        "tel": "13235045698"
      },
      {
        "name": "Wyqtt",
        "tel": "13285384032"
      },
      {
        "name": "Wavzqge",
        "tel": "13071234976"
      }
    ]
  },
  {
    "index": "X",
    "users": [
      {
        "name": "Xcqlzq",
        "tel": "18762157298"
      },
      {
        "name": "Xrrhy",
        "tel": "18764434385"
      },
      {
        "name": "Xwbiawm",
        "tel": "13307426789"
      }
    ]
  },
  {
    "index": "Y",
    "users": [
      {
        "name": "Yahzgc",
        "tel": "13193542552"
      },
      {
        "name": "Ycwxo",
        "tel": "13582101495"
      },
      {
        "name": "Ybew",
        "tel": "17008997341"
      },
      {
        "name": "Yhvyw",
        "tel": "13395493201"
      }
    ]
  },
  {
    "index": "Z",
    "users": [
      {
        "name": "Zhhdvdh",
        "tel": "13170724941"
      },
      {
        "name": "Zpuur",
        "tel": "18941604179"
      },
      {
        "name": "Ztdxa",
        "tel": "18912562199"
      },
      {
        "name": "Zewpieq",
        "tel": "13815173598"
      },
      {
        "name": "Zlfv",
        "tel": "13085397239"
      }
    ]
  }]